{"hash":"ar8trp3g9s","parent_hash":"n6gehqauef","thumbUrl":"https://saved-work.desmos.com/calc_thumbs/production/ar8trp3g9s.png","stateUrl":"https://saved-work.desmos.com/calc-states/production/ar8trp3g9s","title":"Hitting the Target","access":"link","created":"Thu, 07 May 2020 15:22:25 GMT","state":{"version":7,"graph":{"viewport":{"xmin":-25.386671434560856,"ymin":-9.717779105525302,"xmax":20.135552207422844,"ymax":17.680218708291314}},"randomSeed":"68d5f97787814234f58291bb3f481e1b","expressions":{"list":[{"type":"expression","id":"1","color":"#c74440","latex":"d=8.67","slider":{"hardMin":true,"hardMax":true,"min":"1","max":"50","step":"0.01"}},{"type":"expression","id":"2","color":"#2d70b3","latex":"h=-0.2","slider":{"hardMin":true,"hardMax":true,"max":"20","step":"0.01"}},{"type":"expression","id":"3","color":"#000000","latex":"\\left(d,h\\right)"},{"type":"expression","id":"4","color":"#6042a6","latex":"a=2.5607963267948968","slider":{"hardMin":true,"hardMax":true,"min":"\\frac{\\pi}{2}","max":"\\frac{3}{2}\\pi","step":"0.01"}},{"type":"expression","id":"5","color":"#000000","latex":"v=21","slider":{"hardMin":true,"hardMax":true,"min":"0","max":"50","step":"0.01"}},{"type":"expression","id":"6","color":"#c74440","latex":"\\left(d+v\\cos\\left(a\\right),h+v\\sin\\left(a\\right)\\right)"},{"type":"expression","id":"10","color":"#000000","latex":"v_{x}=v\\cos\\left(a\\right)"},{"type":"expression","id":"11","color":"#c74440","latex":"v_{y}=v\\sin\\left(a\\right)"},{"type":"expression","id":"15","color":"#000000","latex":"\\left(v_{x},v_{y}\\right)"},{"type":"expression","id":"7","color":"#2d70b3","latex":"g=9.8","slider":{"hardMin":true,"hardMax":true,"min":"9","max":"12","step":"0.001"}},{"type":"expression","id":"8","color":"#000000","latex":"\\left(d+v_{x}t,h+v_{y}t-\\frac{1}{2}gt^{2}\\right)","parametricDomain":{"min":"0","max":"10"},"domain":{"min":"0","max":"10"}},{"type":"expression","id":"9","color":"#6042a6","latex":"\\left(0,h-v_{y}\\cdot\\frac{d}{v_{x}}-\\frac{1}{2}g\\cdot\\frac{d^{2}}{v_{x}^{2}}\\right)","dragMode":"NONE"},{"type":"expression","id":"12","color":"#2d70b3","latex":"Y=\\left(0,5.4\\right)","dragMode":"Y"},{"type":"expression","id":"13","color":"#388c46","latex":"c\\left(t\\right)=\\operatorname{abs}\\left(t-\\frac{Y.y}{2}\\right)-\\frac{Y.y}{2}","hidden":true},{"type":"expression","id":"14","color":"#6042a6","latex":"c\\left(h-y\\cdot\\frac{d}{x}-\\frac{1}{2}g\\cdot\\frac{d^{2}}{x^{2}}\\right)<0\\left\\{x<0\\right\\}"},{"type":"expression","id":"16","color":"#fa7e19","latex":"y=\\frac{h-Y.y}{d}x","lineStyle":"DASHED"},{"type":"expression","id":"17","color":"#fa7e19","latex":"y=\\frac{h}{d}x","lineStyle":"DASHED"}]}}}